{"cameraMode":{"drawMode":0,"name":"Shaded","section":"Shading Mode"},"sceneLighting":false,"audioPlay":false,"sceneViewState":{"m_AlwaysRefresh":false,"showFog":true,"showSkybox":false,"showFlares":true,"showImageEffects":true,"showParticleSystems":true,"showVisualEffectGraphs":true,"m_FxEnabled":true},"in2DMode":false,"pivot":{"x":0.497316837310791,"y":0.593612551689148,"z":1.1460062265396119},"rotation":{"x":0.13071982562541963,"y":0.7380197048187256,"z":-0.14938482642173768,"w":0.6450868844985962},"size":0.7460535764694214,"orthographic":false}